LICENSE.md
magic_combo/__init__.py
magic_combo/__main__.py
magic_combo/command.py
magic_combo/config.py
magic_combo/constants.py
magic_combo/playbooks.py
magic_combo/scripts/__init__.py
magic_combo/scripts/bump_version.py
magic_combo/scripts/generate_credits.py
magic_combo/tasks.py
magic_combo-0.2.4.dist-info/LICENSE.md
magic_combo-0.2.4.dist-info/METADATA
magic_combo-0.2.4.dist-info/WHEEL
magic_combo-0.2.4.dist-info/entry_points.txt
magic_combo-0.2.4.dist-info/RECORD
