Metadata-Version: 2.1
Name: magic_combo
Version: 0.2.4
Summary: Utilities for games project management
Home-page: https://github.com/MechanicalFlower/magic_combo
License: MIT
Author: Florian Vazelle
Author-email: florian.vazelle@vivaldi.net
Requires-Python: >=3.10,<4.0
Classifier: License :: OSI Approved :: MIT License
Classifier: Programming Language :: Python :: 3
Classifier: Programming Language :: Python :: 3.10
Classifier: Programming Language :: Python :: 3.11
Requires-Dist: gdscript-docs-maker (>=1.5.1,<2.0.0)
Requires-Dist: gdtoolkit (>=4.0.0,<5.0.0)
Requires-Dist: invoke (>=2.2.0,<3.0.0)
Requires-Dist: mkdocs (>=1.5.2,<2.0.0)
Requires-Dist: pre-commit (>=3.3.3,<4.0.0)
Requires-Dist: reuse (>=2.1.0,<3.0.0)
Project-URL: Bug Tracker, https://github.com/MechanicalFlower/magic_combo/issues
Project-URL: Changelog, https://github.com/MechanicalFlower/magic_combo/blob/main/CHANGELOG.md
Project-URL: Repository, https://github.com/MechanicalFlower/magic_combo
